terraform_install/__init__.py
terraform_install/cli/__init__.py
terraform_install/cli/root.py
terraform_install/constants.py
terraform_install/install.py
terraform_install/is_installed.py
terraform_install/terraform.py
terraform_install/version.py
terraform_install-0.4.0.dist-info/entry_points.txt
terraform_install-0.4.0.dist-info/WHEEL
terraform_install-0.4.0.dist-info/METADATA
terraform_install-0.4.0.dist-info/RECORD
