Metadata-Version: 2.1
Name: terraform-install
Version: 0.4.0
Summary: Wrapper which installs Terraform
Home-page: https://github.com/joshwycuff/python-terraform-utils/packages/terraform_install
License: MIT
Keywords: terraform
Author: Josh Wycuff
Author-email: Joshua.Wycuff@turner.com
Requires-Python: >=3.6,<4.0
Classifier: License :: OSI Approved :: MIT License
Classifier: Programming Language :: Python :: 3
Classifier: Programming Language :: Python :: 3.10
Classifier: Programming Language :: Python :: 3.6
Classifier: Programming Language :: Python :: 3.7
Classifier: Programming Language :: Python :: 3.8
Classifier: Programming Language :: Python :: 3.9
Requires-Dist: terraform_version
Project-URL: Documentation, https://github.com/joshwycuff/python-terraform-utils/packages/terraform_install
Project-URL: Repository, https://github.com/joshwycuff/python-terraform-utils
